README.txt
buildout.cfg
setup.py
test-plone-3.3.x.cfg
test-plone-4.0.x.cfg
collective/__init__.py
collective.flag.egg-info/PKG-INFO
collective.flag.egg-info/SOURCES.txt
collective.flag.egg-info/dependency_links.txt
collective.flag.egg-info/entry_points.txt
collective.flag.egg-info/namespace_packages.txt
collective.flag.egg-info/not-zip-safe
collective.flag.egg-info/requires.txt
collective.flag.egg-info/top_level.txt
collective/flag/__init__.py
collective/flag/configure.zcml
collective/flag/interfaces.py
collective/flag/profiles.zcml
collective/flag/schemaextender.py
collective/flag/locales/collective.flag.pot
collective/flag/locales/de/LC_MESSAGES/collective.flag.po
collective/flag/locales/en/LC_MESSAGES/collective.flag.po
collective/flag/locales/nl/LC_MESSAGES/collective.flag.po
collective/flag/locales/no/LC_MESSAGES/collective.flag.po
collective/flag/locales/ru/LC_MESSAGES/collective.flag.po
collective/flag/locales/uk/LC_MESSAGES/collective.flag.po
collective/flag/profiles/catalog.xml
collective/flag/profiles/portal_atct.xml
collective/flag/profiles/registry.xml
collective/flag/tests/__init__.py
collective/flag/tests/base.py
collective/flag/tests/test_integration_unit.py
docs/HISTORY.txt
docs/INSTALL.txt
docs/LICENSE.GPL
docs/LICENSE.txt