Metadata-Version: 1.0
Name: collective.flag
Version: 1.3
Summary: Makes it possible to flag items as 'special'.
Home-page: http://plone.org/products/collective.flag
Author: Jarn [Denys Mishunov]
Author-email: info@jarn.com
License: GPL
Keywords: plone zope flag important
Platform: UNKNOWN
Classifier: Framework :: Plone
Classifier: Programming Language :: Python
Classifier: Topic :: Software Development :: Libraries :: Python Modules
